git_sim/__init__.py
git_sim/__main__.py
git_sim/add.py
git_sim/animations.py
git_sim/branch.py
git_sim/checkout.py
git_sim/cherrypick.py
git_sim/clean.py
git_sim/clone.py
git_sim/commands.py
git_sim/commit.py
git_sim/config.py
git_sim/enums.py
git_sim/fetch.py
git_sim/git_sim_base_command.py
git_sim/init.py
git_sim/log.py
git_sim/logo.png
git_sim/merge.py
git_sim/mv.py
git_sim/pull.py
git_sim/push.py
git_sim/rebase.py
git_sim/remote.py
git_sim/reset.py
git_sim/restore.py
git_sim/revert.py
git_sim/rm.py
git_sim/settings.py
git_sim/stash.py
git_sim/status.py
git_sim/switch.py
git_sim/tag.py
git_sim-0.3.5.dist-info/LICENSE
git_sim-0.3.5.dist-info/METADATA
git_sim-0.3.5.dist-info/WHEEL
git_sim-0.3.5.dist-info/entry_points.txt
git_sim-0.3.5.dist-info/top_level.txt
git_sim-0.3.5.dist-info/RECORD
