Metadata-Version: 2.1
Name: git-sim
Version: 0.3.5
Summary: Simulate Git commands on your own repos by generating an image (default) or video visualization depicting the command's behavior.
Author-email: Jacob Stopak <jacob@initialcommit.io>
License: GPL-2.0
Project-URL: Homepage, https://initialcommit.com/tools/git-sim
Project-URL: Source, https://github.com/initialcommit-com/git-sim
Keywords: git,sim,simulation,simulate,git-simulate,git-simulation,git-sim,manim,animation,gitanimation,image,video,dryrun,dry-run
Classifier: Programming Language :: Python :: 3
Classifier: License :: OSI Approved :: GNU General Public License v2 (GPLv2)
Classifier: Operating System :: OS Independent
Requires-Python: >=3.7
License-File: LICENSE
Requires-Dist: git-dummy
Requires-Dist: gitpython
Requires-Dist: manim
Requires-Dist: opencv-python-headless
Requires-Dist: pydantic-settings
Requires-Dist: typer
Requires-Dist: fonttools
Provides-Extra: dev
Requires-Dist: black ; extra == 'dev'
Requires-Dist: numpy ; extra == 'dev'
Requires-Dist: pillow ; extra == 'dev'
Requires-Dist: pytest ; extra == 'dev'
